BFEE2/__init__.py
BFEE2/gui.py
BFEE2/inputGenerator.py
BFEE2/postTreatment.py
BFEE2/version.py
BFEE2/commonTools/__init__.py
BFEE2/commonTools/commonSlots.py
BFEE2/commonTools/fileParser.py
BFEE2/commonTools/ploter.py
BFEE2/doc/Doc.pdf
BFEE2/doc/__init__.py
BFEE2/templates_gromacs/000.colvars.template
BFEE2/templates_gromacs/000.generate_tpr_sh.template
BFEE2/templates_gromacs/000.mdp.template
BFEE2/templates_gromacs/001.colvars.template
BFEE2/templates_gromacs/001.generate_tpr_sh.template
BFEE2/templates_gromacs/001.mdp.template
BFEE2/templates_gromacs/001.readme.template
BFEE2/templates_gromacs/002.colvars.template
BFEE2/templates_gromacs/002.generate_tpr_sh.template
BFEE2/templates_gromacs/002.mdp.template
BFEE2/templates_gromacs/003.colvars.template
BFEE2/templates_gromacs/003.generate_tpr_sh.template
BFEE2/templates_gromacs/003.mdp.template
BFEE2/templates_gromacs/004.colvars.template
BFEE2/templates_gromacs/004.generate_tpr_sh.template
BFEE2/templates_gromacs/004.mdp.template
BFEE2/templates_gromacs/005.colvars.template
BFEE2/templates_gromacs/005.generate_tpr_sh.template
BFEE2/templates_gromacs/005.mdp.template
BFEE2/templates_gromacs/006.colvars.template
BFEE2/templates_gromacs/006.generate_tpr_sh.template
BFEE2/templates_gromacs/006.mdp.template
BFEE2/templates_gromacs/007.colvars.template
BFEE2/templates_gromacs/007.generate_tpr_sh.template
BFEE2/templates_gromacs/007.mdp.template
BFEE2/templates_gromacs/007_eq.colvars.template
BFEE2/templates_gromacs/007_eq.generate_tpr_sh.template
BFEE2/templates_gromacs/007_min.mdp.template
BFEE2/templates_gromacs/008.colvars.template
BFEE2/templates_gromacs/008.generate_tpr_sh.template
BFEE2/templates_gromacs/008.mdp.template
BFEE2/templates_gromacs/008_eq.generate_tpr_sh.template
BFEE2/templates_gromacs/BFEEGromacs.py
BFEE2/templates_gromacs/__init__.py
BFEE2/templates_gromacs/find_min_max.awk
BFEE2/templates_namd/__init__.py
BFEE2/templates_namd/configTemplate.py
BFEE2/templates_namd/fep.tcl
bfee2-3.0.0.dist-info/licenses/LICENSE
bfee2-3.0.0.dist-info/METADATA
bfee2-3.0.0.dist-info/WHEEL
bfee2-3.0.0.dist-info/top_level.txt
bfee2-3.0.0.dist-info/RECORD
