Metadata-Version: 2.4
Name: bfee2
Version: 3.0.0
Summary: Binding Free Energy Estimator 2
Home-page: https://github.com/fhh2626/BFEE2
Author: Haohao Fu, Haochuan Chen, Hengwei Bian, Wensheng Cai, Chris Chipot
Author-email: fhh2626@nankai.edu.cn
Maintainer: Haohao Fu
Maintainer-email: fhh2626@nankai.edu.cn
License: GPLv3
Requires-Python: >=3.6
License-File: LICENSE
Requires-Dist: setuptools
Requires-Dist: pyside6
Requires-Dist: appdirs
Requires-Dist: MDAnalysis
Requires-Dist: matplotlib
Requires-Dist: numpy
Requires-Dist: scipy
Requires-Dist: parmed
Dynamic: license-file
